README.txt
setup.py
pycurry/__init__.py
pycurry/dbc.py
pycurry/err.py
pycurry/gof.py
pycurry/log.ini
pycurry/log.py
pycurry/pylint.ini
pycurry/thd.py
pycurry/tst.py
pycurry.egg-info/PKG-INFO
pycurry.egg-info/SOURCES.txt
pycurry.egg-info/dependency_links.txt
pycurry.egg-info/requires.txt
pycurry.egg-info/top_level.txt
pycurry.egg-info/zip-safe
pycurry/doc/__init__.py
pycurry/doc/conf.py
pycurry/test/__init__.py
pycurry/test/__main__.py
pycurry/test/all.py
pycurry/test/dbc.py
pycurry/test/err.py
pycurry/test/gof.py
pycurry/test/log.py
pycurry/test/thd.py
pycurry/test/tst.py
pycurry/test/xyz.py
pycurry/doc/Makefile
pycurry/doc/conf.py
pycurry/doc/dbc.rst
pycurry/doc/err.rst
pycurry/doc/gof.rst
pycurry/doc/index.rst
pycurry/doc/make.bat
pycurry/doc/tst.rst
pycurry/test/__init__.py
pycurry/test/__main__.py
pycurry/test/all.py
pycurry/test/dbc.py
pycurry/test/err.py
pycurry/test/gof.py
pycurry/test/log.py
pycurry/test/thd.py
pycurry/test/tst.py
pycurry/test/xyz.py