Metadata-Version: 1.0
Name: pycurry
Version: 1.0
Summary: Facilities to spec, test and run concurrent programs.
Home-page: http://www.fonsdijkstra.nl/pycurry
Author: Fons Dijkstra
Author-email: fons.dijkstra@gmail.com
License: UNKNOWN
Platform: UNKNOWN
Classifier: Development Status :: 4 - Beta
Classifier: Intended Audience :: Developers
Classifier: License :: OSI Approved :: MIT License
Classifier: Natural Language :: English
Classifier: Operating System :: OS Independent
Classifier: Programming Language :: Python
Classifier: Topic :: Documentation
Classifier: Topic :: Software Development :: Testing
Classifier: Topic :: Software Development :: Quality Assurance
Classifier: Topic :: Software Development :: Libraries :: Python Modules
Classifier: Topic :: System :: Hardware :: Symmetric Multi-processing
